[
  {
    "eu_id": "EU-0001",
    "kind": "visual_panel",
    "page": "eastmoney_1746461e6e00efee224a9209974b4bb6de3b11e339e4d86c41569eeddcc3c20e.pdf_8",
    "primary_id": "docling_eastmoney_1746461e6e00efee224a9209974b4bb6de3b11e339e4d86c41569eeddcc3c20e.pdf_8_89",
    "source": "visual_seed",
    "member_count": 33,
    "elements": [
      {
        "id": "docling_eastmoney_1746461e6e00efee224a9209974b4bb6de3b11e339e4d86c41569eeddcc3c20e.pdf_8_89",
        "observed_type": "picture",
        "canon_role": "picture",
        "text": "",
        "bbox": [
          0.12029892761156666,
          0.012386439446966685,
          0.2216412729911389,
          0.04466825879094131
        ],
        "order": 1
      },
      {
        "id": "docling_eastmoney_1746461e6e00efee224a9209974b4bb6de3b11e339e4d86c41569eeddcc3c20e.pdf_8_30",
        "observed_type": "text",
        "canon_role": "support_paragraph",
        "text": "-60",
        "bbox": [
          0.466119096662495,
          0.31976744196547713,
          0.4887063659145071,
          0.32703488350690674
        ],
        "order": 39
      },
      {
        "id": "docling_eastmoney_1746461e6e00efee224a9209974b4bb6de3b11e339e4d86c41569eeddcc3c20e.pdf_8_19",
        "observed_type": "text",
        "canon_role": "support_paragraph",
        "text": "45",
        "bbox": [
          0.09034907645925261,
          0.3197674420495978,
          0.10677618076182878,
          0.3284883717100922
        ],
        "order": 40
      },
      {
        "id": "docling_eastmoney_1746461e6e00efee224a9209974b4bb6de3b11e339e4d86c41569eeddcc3c20e.pdf_8_70",
        "observed_type": "text",
        "canon_role": "support_paragraph",
        "text": "200",
        "bbox": [
          0.5297741268986348,
          0.3284883723070468,
          0.5523613961506467,
          0.3357558138484764
        ],
        "order": 41
      },
      {
        "id": "docling_eastmoney_1746461e6e00efee224a9209974b4bb6de3b11e339e4d86c41569eeddcc3c20e.pdf_8_80",
        "observed_type": "text",
        "canon_role": "support_paragraph",
        "text": "5",
        "bbox": [
          0.9096509242203668,
          0.3415697676309931,
          0.9219712527816867,
          0.3502906972914873
        ],
        "order": 44
      },
      {
        "id": "docling_eastmoney_1746461e6e00efee224a9209974b4bb6de3b11e339e4d86c41569eeddcc3c20e.pdf_8_71",
        "observed_type": "text",
        "canon_role": "support_paragraph",
        "text": "150",
        "bbox": [
          0.5277207397552481,
          0.3473837210170759,
          0.5544147847485162,
          0.3546511625585055
        ],
        "order": 45
      },
      {
        "id": "docling_eastmoney_1746461e6e00efee224a9209974b4bb6de3b11e339e4d86c41569eeddcc3c20e.pdf_8_21",
        "observed_type": "text",
        "canon_role": "support_paragraph",
        "text": "35",
        "bbox": [
          0.09034907645925261,
          0.3502906978635513,
          0.10677618076182878,
          0.3590116275240456
        ],
        "order": 46
      },
      {
        "id": "docling_eastmoney_1746461e6e00efee224a9209974b4bb6de3b11e339e4d86c41569eeddcc3c20e.pdf_8_72",
        "observed_type": "text",
        "canon_role": "support_paragraph",
        "text": "100",
        "bbox": [
          0.5277207387898093,
          0.3662790699996341,
          0.5523613959124494,
          0.3735465115410637
        ],
        "order": 50
      },
      {
        "id": "docling_eastmoney_1746461e6e00efee224a9209974b4bb6de3b11e339e4d86c41569eeddcc3c20e.pdf_8_23",
        "observed_type": "text",
        "canon_role": "support_paragraph",
        "text": "25",
        "bbox": [
          0.09034907645925261,
          0.38226744194730844,
          0.10677618076182878,
          0.38953488348873805
        ],
        "order": 52
      },
      {
        "id": "docling_eastmoney_1746461e6e00efee224a9209974b4bb6de3b11e339e4d86c41569eeddcc3c20e.pdf_8_74",
        "observed_type": "text",
        "canon_role": "support_paragraph",
        "text": "N*",
        "bbox": [
          0.5646817249982324,
          0.3953488379557848,
          0.5913757699915005,
          0.4127906972767735
        ],
        "order": 54
      },
      {
        "id": "docling_eastmoney_1746461e6e00efee224a9209974b4bb6de3b11e339e4d86c41569eeddcc3c20e.pdf_8_36",
        "observed_type": "text",
        "canon_role": "support_paragraph",
        "text": "60",
        "bbox": [
          0.4681724850150364,
          0.44331395370172966,
          0.4845995893176126,
          0.45203488336222397
        ],
        "order": 61
      },
      {
        "id": "docling_eastmoney_1746461e6e00efee224a9209974b4bb6de3b11e339e4d86c41569eeddcc3c20e.pdf_8_27",
        "observed_type": "text",
        "canon_role": "support_paragraph",
        "text": "5",
        "bbox": [
          0.09650924024879128,
          0.44476744174811994,
          0.10472279240007938,
          0.4505813951704846
        ],
        "order": 62
      },
      {
        "id": "docling_eastmoney_1746461e6e00efee224a9209974b4bb6de3b11e339e4d86c41569eeddcc3c20e.pdf_8_76",
        "observed_type": "text",
        "canon_role": "support_paragraph",
        "text": "-100",
        "bbox": [
          0.5236139638627172,
          0.44476744194730844,
          0.5544147845972415,
          0.45203488348873794
        ],
        "order": 63
      },
      {
        "id": "docling_eastmoney_1746461e6e00efee224a9209974b4bb6de3b11e339e4d86c41569eeddcc3c20e.pdf_8_82",
        "observed_type": "text",
        "canon_role": "support_paragraph",
        "text": "-1",
        "bbox": [
          0.9096509238853264,
          0.44476744209265734,
          0.9240246403172746,
          0.4520348836340869
        ],
        "order": 64
      },
      {
        "id": "docling_eastmoney_1746461e6e00efee224a9209974b4bb6de3b11e339e4d86c41569eeddcc3c20e.pdf_8_39",
        "observed_type": "text",
        "canon_role": "support_paragraph",
        "text": "(125, tA)",
        "bbox": [
          0.33511570852148925,
          0.5232558143364195,
          0.406570838757501,
          0.5319940477929553
        ],
        "order": 74
      },
      {
        "id": "docling_eastmoney_1746461e6e00efee224a9209974b4bb6de3b11e339e4d86c41569eeddcc3c20e.pdf_8_40",
        "observed_type": "text",
        "canon_role": "support_paragraph",
        "text": "49000",
        "bbox": [
          0.08213552458038494,
          0.5319767442910585,
          0.11704312105616536,
          0.539244185832488
        ],
        "order": 75
      },
      {
        "id": "docling_eastmoney_1746461e6e00efee224a9209974b4bb6de3b11e339e4d86c41569eeddcc3c20e.pdf_8_48",
        "observed_type": "text",
        "canon_role": "support_paragraph",
        "text": "5600",
        "bbox": [
          0.45585215589864736,
          0.5319767445447527,
          0.48459958876254355,
          0.5406976742052472
        ],
        "order": 76
      },
      {
        "id": "docling_eastmoney_1746461e6e00efee224a9209974b4bb6de3b11e339e4d86c41569eeddcc3c20e.pdf_8_41",
        "observed_type": "text",
        "canon_role": "support_paragraph",
        "text": "5171At* (t‡h)",
        "bbox": [
          0.21149897500319673,
          0.5348837211435901,
          0.3182751549762694,
          0.5436507937871425
        ],
        "order": 77
      },
      {
        "id": "docling_eastmoney_1746461e6e00efee224a9209974b4bb6de3b11e339e4d86c41569eeddcc3c20e.pdf_8_49",
        "observed_type": "text",
        "canon_role": "support_paragraph",
        "text": "5400",
        "bbox": [
          0.4579055443411483,
          0.5465116277534979,
          0.48459958933441644,
          0.5552325583600978
        ],
        "order": 78
      },
      {
        "id": "docling_eastmoney_1746461e6e00efee224a9209974b4bb6de3b11e339e4d86c41569eeddcc3c20e.pdf_8_42",
        "observed_type": "text",
        "canon_role": "support_paragraph",
        "text": "47000",
        "bbox": [
          0.08213552356224668,
          0.5523255816275412,
          0.11704312003802712,
          0.5595930231689706
        ],
        "order": 79
      },
      {
        "id": "docling_eastmoney_1746461e6e00efee224a9209974b4bb6de3b11e339e4d86c41569eeddcc3c20e.pdf_8_50",
        "observed_type": "text",
        "canon_role": "support_paragraph",
        "text": "5200",
        "bbox": [
          0.45790554413580936,
          0.561046511407344,
          0.4845995891290776,
          0.5697674420139438
        ],
        "order": 80
      },
      {
        "id": "docling_eastmoney_1746461e6e00efee224a9209974b4bb6de3b11e339e4d86c41569eeddcc3c20e.pdf_8_43",
        "observed_type": "text",
        "canon_role": "support_paragraph",
        "text": "45000",
        "bbox": [
          0.08213552486991688,
          0.5712209303194014,
          0.11909650921632536,
          0.5784883718608309
        ],
        "order": 81
      },
      {
        "id": "docling_eastmoney_1746461e6e00efee224a9209974b4bb6de3b11e339e4d86c41569eeddcc3c20e.pdf_8_51",
        "observed_type": "text",
        "canon_role": "support_paragraph",
        "text": "5000",
        "bbox": [
          0.45790554447804077,
          0.5755813954895204,
          0.48459958947130893,
          0.5843023251500148
        ],
        "order": 82
      },
      {
        "id": "docling_eastmoney_1746461e6e00efee224a9209974b4bb6de3b11e339e4d86c41569eeddcc3c20e.pdf_8_44",
        "observed_type": "text",
        "canon_role": "support_paragraph",
        "text": "43000",
        "bbox": [
          0.08213552370769502,
          0.5915697676558841,
          0.11704312018347543,
          0.5988372091973136
        ],
        "order": 83
      },
      {
        "id": "docling_eastmoney_1746461e6e00efee224a9209974b4bb6de3b11e339e4d86c41569eeddcc3c20e.pdf_8_52",
        "observed_type": "text",
        "canon_role": "support_paragraph",
        "text": "4800",
        "bbox": [
          0.4579055439048034,
          0.5915697676558841,
          0.4845995888980716,
          0.5988372091973136
        ],
        "order": 84
      },
      {
        "id": "docling_eastmoney_1746461e6e00efee224a9209974b4bb6de3b11e339e4d86c41569eeddcc3c20e.pdf_8_53",
        "observed_type": "text",
        "canon_role": "support_paragraph",
        "text": "4600",
        "bbox": [
          0.45790554413580936,
          0.6061046510578305,
          0.4845995891290776,
          0.6133720930723128
        ],
        "order": 85
      },
      {
        "id": "docling_eastmoney_1746461e6e00efee224a9209974b4bb6de3b11e339e4d86c41569eeddcc3c20e.pdf_8_45",
        "observed_type": "text",
        "canon_role": "support_paragraph",
        "text": "41000",
        "bbox": [
          0.08418891202185914,
          0.6104651161793504,
          0.1170431206270115,
          0.6177325581938325
        ],
        "order": 86
      },
      {
        "id": "docling_eastmoney_1746461e6e00efee224a9209974b4bb6de3b11e339e4d86c41569eeddcc3c20e.pdf_8_54",
        "observed_type": "text",
        "canon_role": "support_paragraph",
        "text": "4400",
        "bbox": [
          0.4579055439048034,
          0.6206395350977445,
          0.4845995888980716,
          0.627906976639174
        ],
        "order": 87
      },
      {
        "id": "docling_eastmoney_1746461e6e00efee224a9209974b4bb6de3b11e339e4d86c41569eeddcc3c20e.pdf_8_46",
        "observed_type": "text",
        "canon_role": "support_paragraph",
        "text": "39000",
        "bbox": [
          0.08213552396436852,
          0.6308139537387328,
          0.11704312044014896,
          0.6380813952801624
        ],
        "order": 88
      },
      {
        "id": "docling_eastmoney_1746461e6e00efee224a9209974b4bb6de3b11e339e4d86c41569eeddcc3c20e.pdf_8_55",
        "observed_type": "text",
        "canon_role": "support_paragraph",
        "text": "4200",
        "bbox": [
          0.4579055439048034,
          0.6351744188186746,
          0.4845995888980716,
          0.6424418603601042
        ],
        "order": 89
      },
      {
        "id": "docling_eastmoney_1746461e6e00efee224a9209974b4bb6de3b11e339e4d86c41569eeddcc3c20e.pdf_8_56",
        "observed_type": "text",
        "canon_role": "support_paragraph",
        "text": "- 4000",
        "bbox": [
          0.4435318276905961,
          0.6497093025093239,
          0.4845995877782608,
          0.6569940476102687
        ],
        "order": 90
      },
      {
        "id": "docling_eastmoney_1746461e6e00efee224a9209974b4bb6de3b11e339e4d86c41569eeddcc3c20e.pdf_8_47",
        "observed_type": "text",
        "canon_role": "support_paragraph",
        "text": "37000 +",
        "bbox": [
          0.08213552317202535,
          0.649709302756962,
          0.1334702252879336,
          0.6584821428594757
        ],
        "order": 91
      },
      {
        "id": "docling_eastmoney_1746461e6e00efee224a9209974b4bb6de3b11e339e4d86c41569eeddcc3c20e.pdf_8_87",
        "observed_type": "text",
        "canon_role": "support_paragraph",
        "text": "106% 111% ТНТТНТ ТАНН Н60 КГ",
        "bbox": [
          0.30184804496065487,
          0.8501984125902331,
          0.942505116590468,
          0.9273313491789014
        ],
        "order": 95
      }
    ]
  },
  {
    "eu_id": "EU-0002",
    "kind": "visual_panel",
    "page": "eastmoney_1746461e6e00efee224a9209974b4bb6de3b11e339e4d86c41569eeddcc3c20e.pdf_8",
    "primary_id": "docling_eastmoney_1746461e6e00efee224a9209974b4bb6de3b11e339e4d86c41569eeddcc3c20e.pdf_8_90",
    "source": "visual_seed",
    "member_count": 20,
    "elements": [
      {
        "id": "docling_eastmoney_1746461e6e00efee224a9209974b4bb6de3b11e339e4d86c41569eeddcc3c20e.pdf_8_1",
        "observed_type": "section_header",
        "canon_role": "section_header",
        "text": "012",
        "bbox": [
          0.08213552729728897,
          0.0654069768147003,
          0.34907597187976397,
          0.07703488365942984
        ],
        "order": 3
      },
      {
        "id": "docling_eastmoney_1746461e6e00efee224a9209974b4bb6de3b11e339e4d86c41569eeddcc3c20e.pdf_8_90",
        "observed_type": "picture",
        "canon_role": "picture",
        "text": "",
        "bbox": [
          0.07393525387672877,
          0.07821070103117318,
          0.49879623468438256,
          0.24925492226746207
        ],
        "order": 4
      },
      {
        "id": "docling_eastmoney_1746461e6e00efee224a9209974b4bb6de3b11e339e4d86c41569eeddcc3c20e.pdf_8_60",
        "observed_type": "text",
        "canon_role": "support_paragraph",
        "text": "0.50",
        "bbox": [
          0.5174537990567497,
          0.11191860486452013,
          0.5420944561793898,
          0.12063953452501455
        ],
        "order": 10
      },
      {
        "id": "docling_eastmoney_1746461e6e00efee224a9209974b4bb6de3b11e339e4d86c41569eeddcc3c20e.pdf_8_61",
        "observed_type": "text",
        "canon_role": "support_paragraph",
        "text": "0.40",
        "bbox": [
          0.5174537990567497,
          0.13808139556219465,
          0.5420944561793898,
          0.14680232522268896
        ],
        "order": 13
      },
      {
        "id": "docling_eastmoney_1746461e6e00efee224a9209974b4bb6de3b11e339e4d86c41569eeddcc3c20e.pdf_8_62",
        "observed_type": "text",
        "canon_role": "support_paragraph",
        "text": "0.30",
        "bbox": [
          0.5174537986460722,
          0.1642441859392221,
          0.5420944557687124,
          0.17151162795370434
        ],
        "order": 18
      },
      {
        "id": "docling_eastmoney_1746461e6e00efee224a9209974b4bb6de3b11e339e4d86c41569eeddcc3c20e.pdf_8_66",
        "observed_type": "caption",
        "canon_role": "support_paragraph",
        "text": "***IR: Wind, HTI, tx ₴ 2022/07/01",
        "bbox": [
          0.5236139676532487,
          0.2514534884572697,
          0.7556468184350467,
          0.2616567458968982
        ],
        "order": 29
      },
      {
        "id": "docling_eastmoney_1746461e6e00efee224a9209974b4bb6de3b11e339e4d86c41569eeddcc3c20e.pdf_8_17",
        "observed_type": "caption",
        "canon_role": "support_paragraph",
        "text": "***/: Wind, HT, # ₴ 2022/07/01",
        "bbox": [
          0.0821355233014309,
          0.2514534886086747,
          0.3121149862126007,
          0.2616567460483032
        ],
        "order": 30
      },
      {
        "id": "docling_eastmoney_1746461e6e00efee224a9209974b4bb6de3b11e339e4d86c41569eeddcc3c20e.pdf_8_68",
        "observed_type": "text",
        "canon_role": "support_paragraph",
        "text": "250 -",
        "bbox": [
          0.5277207401874991,
          0.30803571437150173,
          0.5605749487926515,
          0.31547619056197795
        ],
        "order": 36
      },
      {
        "id": "docling_eastmoney_1746461e6e00efee224a9209974b4bb6de3b11e339e4d86c41569eeddcc3c20e.pdf_8_20",
        "observed_type": "text",
        "canon_role": "support_paragraph",
        "text": "40",
        "bbox": [
          0.09034907645925261,
          0.3357558140403318,
          0.10677618076182878,
          0.34302325558176133
        ],
        "order": 42
      },
      {
        "id": "docling_eastmoney_1746461e6e00efee224a9209974b4bb6de3b11e339e4d86c41569eeddcc3c20e.pdf_8_31",
        "observed_type": "text",
        "canon_role": "support_paragraph",
        "text": "-40",
        "bbox": [
          0.46817248537164985,
          0.3401162791566108,
          0.4887063654154822,
          0.34738372069804035
        ],
        "order": 43
      },
      {
        "id": "docling_eastmoney_1746461e6e00efee224a9209974b4bb6de3b11e339e4d86c41569eeddcc3c20e.pdf_8_81",
        "observed_type": "text",
        "canon_role": "support_paragraph",
        "text": "4",
        "bbox": [
          0.9096509239123586,
          0.35755813958372307,
          0.9219712524736784,
          0.36773255783633507
        ],
        "order": 47
      },
      {
        "id": "docling_eastmoney_1746461e6e00efee224a9209974b4bb6de3b11e339e4d86c41569eeddcc3c20e.pdf_8_22",
        "observed_type": "text",
        "canon_role": "support_paragraph",
        "text": "30",
        "bbox": [
          0.09034907639080635,
          0.3662790698724538,
          0.10677618069338253,
          0.3735465114138834
        ],
        "order": 49
      },
      {
        "id": "docling_eastmoney_1746461e6e00efee224a9209974b4bb6de3b11e339e4d86c41569eeddcc3c20e.pdf_8_73",
        "observed_type": "text",
        "canon_role": "support_paragraph",
        "text": "50",
        "bbox": [
          0.5359342915858782,
          0.38517441874533415,
          0.5523613958884545,
          0.39389534840582857
        ],
        "order": 53
      },
      {
        "id": "docling_eastmoney_1746461e6e00efee224a9209974b4bb6de3b11e339e4d86c41569eeddcc3c20e.pdf_8_35",
        "observed_type": "text",
        "canon_role": "support_paragraph",
        "text": "40",
        "bbox": [
          0.464065708506489,
          0.42296511661355135,
          0.48459958855032126,
          0.4316860462740458
        ],
        "order": 58
      },
      {
        "id": "docling_eastmoney_1746461e6e00efee224a9209974b4bb6de3b11e339e4d86c41569eeddcc3c20e.pdf_8_75",
        "observed_type": "text",
        "canon_role": "support_paragraph",
        "text": "-50",
        "bbox": [
          0.5359342917912171,
          0.4244186050825436,
          0.5523613960937933,
          0.43313953474303785
        ],
        "order": 59
      },
      {
        "id": "docling_eastmoney_1746461e6e00efee224a9209974b4bb6de3b11e339e4d86c41569eeddcc3c20e.pdf_8_37",
        "observed_type": "caption",
        "canon_role": "support_paragraph",
        "text": "****: Wind, HTI",
        "bbox": [
          0.0821355233995389,
          0.4680059522847746,
          0.20739219420826413,
          0.478197674333428
        ],
        "order": 68
      },
      {
        "id": "docling_eastmoney_1746461e6e00efee224a9209974b4bb6de3b11e339e4d86c41569eeddcc3c20e.pdf_8_83",
        "observed_type": "caption",
        "canon_role": "support_paragraph",
        "text": "***#R: Wind, HTI",
        "bbox": [
          0.5236139667660771,
          0.4680059525943099,
          0.6529774133160584,
          0.4781976741699105
        ],
        "order": 69
      },
      {
        "id": "docling_eastmoney_1746461e6e00efee224a9209974b4bb6de3b11e339e4d86c41569eeddcc3c20e.pdf_8_38",
        "observed_type": "caption",
        "canon_role": "support_paragraph",
        "text": "B1620 7 7-10 ARAFEHARE",
        "bbox": [
          0.08213552885307783,
          0.49999999988332067,
          0.3449691976942967,
          0.513144841153162
        ],
        "order": 70
      },
      {
        "id": "docling_eastmoney_1746461e6e00efee224a9209974b4bb6de3b11e339e4d86c41569eeddcc3c20e.pdf_8_85",
        "observed_type": "caption",
        "canon_role": "support_paragraph",
        "text": "***R: Wind, HT, i: 47 Q2-04 ₫ 7201t",
        "bbox": [
          0.5236139673974307,
          0.6860119046811829,
          0.8069815149449304,
          0.6962209300528253
        ],
        "order": 92
      },
      {
        "id": "docling_eastmoney_1746461e6e00efee224a9209974b4bb6de3b11e339e4d86c41569eeddcc3c20e.pdf_8_57",
        "observed_type": "caption",
        "canon_role": "support_paragraph",
        "text": "*****: Wind, HTI",
        "bbox": [
          0.08008213817264788,
          0.6860119049752621,
          0.20944558472262928,
          0.6976744184659694
        ],
        "order": 93
      }
    ]
  },
  {
    "eu_id": "EU-0003",
    "kind": "visual_panel",
    "page": "eastmoney_1746461e6e00efee224a9209974b4bb6de3b11e339e4d86c41569eeddcc3c20e.pdf_8",
    "primary_id": "docling_eastmoney_1746461e6e00efee224a9209974b4bb6de3b11e339e4d86c41569eeddcc3c20e.pdf_8_93",
    "source": "visual_seed",
    "member_count": 1,
    "elements": [
      {
        "id": "docling_eastmoney_1746461e6e00efee224a9209974b4bb6de3b11e339e4d86c41569eeddcc3c20e.pdf_8_93",
        "observed_type": "picture",
        "canon_role": "picture",
        "text": "",
        "bbox": [
          0.5152156511558155,
          0.08083723507767408,
          0.9190949113654399,
          0.2557039297559721
        ],
        "order": 5
      }
    ]
  },
  {
    "eu_id": "EU-0004",
    "kind": "text_cluster_panel",
    "page": "eastmoney_1746461e6e00efee224a9209974b4bb6de3b11e339e4d86c41569eeddcc3c20e.pdf_8",
    "primary_id": "docling_eastmoney_1746461e6e00efee224a9209974b4bb6de3b11e339e4d86c41569eeddcc3c20e.pdf_8_58",
    "source": "text_cluster",
    "member_count": 1,
    "elements": [
      {
        "id": "docling_eastmoney_1746461e6e00efee224a9209974b4bb6de3b11e339e4d86c41569eeddcc3c20e.pdf_8_58",
        "observed_type": "text",
        "canon_role": "support_paragraph",
        "text": "- 1 A *1# (AAA 37#**-= 71*, %)",
        "bbox": [
          0.6221765883903686,
          0.08430232583008941,
          0.8316221725952577,
          0.0944940474056902
        ],
        "order": 6
      }
    ]
  },
  {
    "eu_id": "EU-0005",
    "kind": "table_panel",
    "page": "eastmoney_1746461e6e00efee224a9209974b4bb6de3b11e339e4d86c41569eeddcc3c20e.pdf_8",
    "primary_id": "docling_eastmoney_1746461e6e00efee224a9209974b4bb6de3b11e339e4d86c41569eeddcc3c20e.pdf_8_88",
    "source": "visual_seed",
    "member_count": 3,
    "elements": [
      {
        "id": "docling_eastmoney_1746461e6e00efee224a9209974b4bb6de3b11e339e4d86c41569eeddcc3c20e.pdf_8_59",
        "observed_type": "text",
        "canon_role": "support_paragraph",
        "text": "#AIR *1# (AAA 5##**-3##**, %)",
        "bbox": [
          0.6303901469889523,
          0.09593023266148469,
          0.8501026705469817,
          0.10615079342410197
        ],
        "order": 7
      },
      {
        "id": "docling_eastmoney_1746461e6e00efee224a9209974b4bb6de3b11e339e4d86c41569eeddcc3c20e.pdf_8_84",
        "observed_type": "section_header",
        "canon_role": "section_header",
        "text": "017472 713124 20 4đE J",
        "bbox": [
          0.5215605760273672,
          0.5000000000165571,
          0.782340856997958,
          0.5131448412863984
        ],
        "order": 71
      },
      {
        "id": "docling_eastmoney_1746461e6e00efee224a9209974b4bb6de3b11e339e4d86c41569eeddcc3c20e.pdf_8_88",
        "observed_type": "table",
        "canon_role": "table",
        "text": "# 1) | Q1 | Q2 | Q3 | Q4 | (%) | 2020 | -6.9 | 3.1 | 4.8 | 6.4 | (%) | 2022 | 4.8 | FiFt (%) | 2020 | -24.1 | -18 | -6.6 | 1.9 | FiFt (%) | 2022 | 3.5 | 0.5 | 4 | 5.5 | (%) | 2020 | -10.5 | -5.3 | -2.3 | -0.1 | (%) | 2022 | -6.6",
        "bbox": [
          0.5181999898446947,
          0.5166751491355814,
          0.9363350182086986,
          0.682564424316615
        ],
        "order": 73
      }
    ]
  },
  {
    "eu_id": "EU-0006",
    "kind": "text_cluster_panel",
    "page": "eastmoney_1746461e6e00efee224a9209974b4bb6de3b11e339e4d86c41569eeddcc3c20e.pdf_8",
    "primary_id": "docling_eastmoney_1746461e6e00efee224a9209974b4bb6de3b11e339e4d86c41569eeddcc3c20e.pdf_8_2",
    "source": "text_cluster",
    "member_count": 1,
    "elements": [
      {
        "id": "docling_eastmoney_1746461e6e00efee224a9209974b4bb6de3b11e339e4d86c41569eeddcc3c20e.pdf_8_2",
        "observed_type": "text",
        "canon_role": "support_paragraph",
        "text": "3.30",
        "bbox": [
          0.082135523841144,
          0.1031976746464969,
          0.10677618096378408,
          0.11191860430699133
        ],
        "order": 8
      }
    ]
  },
  {
    "eu_id": "EU-0007",
    "kind": "visual_panel",
    "page": "eastmoney_1746461e6e00efee224a9209974b4bb6de3b11e339e4d86c41569eeddcc3c20e.pdf_8",
    "primary_id": "docling_eastmoney_1746461e6e00efee224a9209974b4bb6de3b11e339e4d86c41569eeddcc3c20e.pdf_8_91",
    "source": "visual_seed",
    "member_count": 29,
    "elements": [
      {
        "id": "docling_eastmoney_1746461e6e00efee224a9209974b4bb6de3b11e339e4d86c41569eeddcc3c20e.pdf_8_10",
        "observed_type": "text",
        "canon_role": "support_paragraph",
        "text": "3.8",
        "bbox": [
          0.4640657091909517,
          0.10319767465618697,
          0.48459958923478397,
          0.1119186043166814
        ],
        "order": 9
      },
      {
        "id": "docling_eastmoney_1746461e6e00efee224a9209974b4bb6de3b11e339e4d86c41569eeddcc3c20e.pdf_8_11",
        "observed_type": "text",
        "canon_role": "support_paragraph",
        "text": "3.3",
        "bbox": [
          0.4620123204817969,
          0.12209302346917131,
          0.4845995897338089,
          0.13081395312966584
        ],
        "order": 11
      },
      {
        "id": "docling_eastmoney_1746461e6e00efee224a9209974b4bb6de3b11e339e4d86c41569eeddcc3c20e.pdf_8_3",
        "observed_type": "text",
        "canon_role": "support_paragraph",
        "text": "3.20",
        "bbox": [
          0.08213552349206803,
          0.12354651152061741,
          0.10677618061470812,
          0.13081395353509964
        ],
        "order": 12
      },
      {
        "id": "docling_eastmoney_1746461e6e00efee224a9209974b4bb6de3b11e339e4d86c41569eeddcc3c20e.pdf_8_12",
        "observed_type": "text",
        "canon_role": "support_paragraph",
        "text": "2.8",
        "bbox": [
          0.4640657091909517,
          0.1409883723306056,
          0.48459958923478397,
          0.1497093019910999
        ],
        "order": 14
      },
      {
        "id": "docling_eastmoney_1746461e6e00efee224a9209974b4bb6de3b11e339e4d86c41569eeddcc3c20e.pdf_8_4",
        "observed_type": "text",
        "canon_role": "support_paragraph",
        "text": "3.10",
        "bbox": [
          0.08213552349206803,
          0.14244186035782672,
          0.10677618061470812,
          0.14970930237230895
        ],
        "order": 15
      },
      {
        "id": "docling_eastmoney_1746461e6e00efee224a9209974b4bb6de3b11e339e4d86c41569eeddcc3c20e.pdf_8_5",
        "observed_type": "text",
        "canon_role": "support_paragraph",
        "text": "3.00",
        "bbox": [
          0.08213552349206803,
          0.16133720919503602,
          0.10677618061470812,
          0.16860465120951826
        ],
        "order": 16
      },
      {
        "id": "docling_eastmoney_1746461e6e00efee224a9209974b4bb6de3b11e339e4d86c41569eeddcc3c20e.pdf_8_13",
        "observed_type": "text",
        "canon_role": "support_paragraph",
        "text": "2.3",
        "bbox": [
          0.4640657085920469,
          0.16133720951634906,
          0.48459958863587915,
          0.16860465105777867
        ],
        "order": 17
      },
      {
        "id": "docling_eastmoney_1746461e6e00efee224a9209974b4bb6de3b11e339e4d86c41569eeddcc3c20e.pdf_8_6",
        "observed_type": "text",
        "canon_role": "support_paragraph",
        "text": "2.90",
        "bbox": [
          0.08213552349206803,
          0.18023255803224525,
          0.10677618061470812,
          0.18750000004672748
        ],
        "order": 19
      },
      {
        "id": "docling_eastmoney_1746461e6e00efee224a9209974b4bb6de3b11e339e4d86c41569eeddcc3c20e.pdf_8_14",
        "observed_type": "text",
        "canon_role": "support_paragraph",
        "text": "1.8",
        "bbox": [
          0.46201232057591046,
          0.18023255822637824,
          0.48459958982792256,
          0.18749999976780782
        ],
        "order": 20
      },
      {
        "id": "docling_eastmoney_1746461e6e00efee224a9209974b4bb6de3b11e339e4d86c41569eeddcc3c20e.pdf_8_63",
        "observed_type": "text",
        "canon_role": "support_paragraph",
        "text": "0.20",
        "bbox": [
          0.5174537986974068,
          0.1889534885491133,
          0.542094455820047,
          0.19767441820960766
        ],
        "order": 21
      },
      {
        "id": "docling_eastmoney_1746461e6e00efee224a9209974b4bb6de3b11e339e4d86c41569eeddcc3c20e.pdf_8_7",
        "observed_type": "text",
        "canon_role": "support_paragraph",
        "text": "2.80",
        "bbox": [
          0.08213552349206803,
          0.19912790686945456,
          0.10677618061470812,
          0.20639534888393699
        ],
        "order": 22
      },
      {
        "id": "docling_eastmoney_1746461e6e00efee224a9209974b4bb6de3b11e339e4d86c41569eeddcc3c20e.pdf_8_15",
        "observed_type": "text",
        "canon_role": "support_paragraph",
        "text": "1.3",
        "bbox": [
          0.4640657091909517,
          0.19912790706358763,
          0.48459958923478397,
          0.20639534860501715
        ],
        "order": 23
      },
      {
        "id": "docling_eastmoney_1746461e6e00efee224a9209974b4bb6de3b11e339e4d86c41569eeddcc3c20e.pdf_8_64",
        "observed_type": "text",
        "canon_role": "support_paragraph",
        "text": "0.10",
        "bbox": [
          0.5174537986460722,
          0.2151162789624779,
          0.5420944557687124,
          0.22238372097696013
        ],
        "order": 24
      },
      {
        "id": "docling_eastmoney_1746461e6e00efee224a9209974b4bb6de3b11e339e4d86c41569eeddcc3c20e.pdf_8_8",
        "observed_type": "text",
        "canon_role": "support_paragraph",
        "text": "2.70",
        "bbox": [
          0.08213552349206803,
          0.21802325570666387,
          0.10677618061470812,
          0.2252906977211462
        ],
        "order": 25
      },
      {
        "id": "docling_eastmoney_1746461e6e00efee224a9209974b4bb6de3b11e339e4d86c41569eeddcc3c20e.pdf_8_16",
        "observed_type": "text",
        "canon_role": "support_paragraph",
        "text": "0.8",
        "bbox": [
          0.4620123198230016,
          0.2180232560461457,
          0.4845995890750136,
          0.2252906975875753
        ],
        "order": 26
      },
      {
        "id": "docling_eastmoney_1746461e6e00efee224a9209974b4bb6de3b11e339e4d86c41569eeddcc3c20e.pdf_8_65",
        "observed_type": "text",
        "canon_role": "support_paragraph",
        "text": "21/11",
        "bbox": [
          0.7474332636425686,
          0.2252906982808183,
          0.7597535948789919,
          0.24563953478604217
        ],
        "order": 27
      },
      {
        "id": "docling_eastmoney_1746461e6e00efee224a9209974b4bb6de3b11e339e4d86c41569eeddcc3c20e.pdf_8_9",
        "observed_type": "text",
        "canon_role": "support_paragraph",
        "text": "=",
        "bbox": [
          0.30390143768924727,
          0.22819767476419792,
          0.3141683777111634,
          0.2383720930168099
        ],
        "order": 28
      },
      {
        "id": "docling_eastmoney_1746461e6e00efee224a9209974b4bb6de3b11e339e4d86c41569eeddcc3c20e.pdf_8_18",
        "observed_type": "section_header",
        "canon_role": "section_header",
        "text": "14",
        "bbox": [
          0.0800821332425162,
          0.28197674419654745,
          0.2854209417061491,
          0.2950581396333944
        ],
        "order": 32
      },
      {
        "id": "docling_eastmoney_1746461e6e00efee224a9209974b4bb6de3b11e339e4d86c41569eeddcc3c20e.pdf_8_91",
        "observed_type": "picture",
        "canon_role": "picture",
        "text": "",
        "bbox": [
          0.0760201358449214,
          0.29895473576448267,
          0.4973875919881726,
          0.4647023697192978
        ],
        "order": 33
      },
      {
        "id": "docling_eastmoney_1746461e6e00efee224a9209974b4bb6de3b11e339e4d86c41569eeddcc3c20e.pdf_8_79",
        "observed_type": "text",
        "canon_role": "support_paragraph",
        "text": "- 7",
        "bbox": [
          0.9014373720088805,
          0.3066860465604674,
          0.9199178641820848,
          0.3169642856971179
        ],
        "order": 35
      },
      {
        "id": "docling_eastmoney_1746461e6e00efee224a9209974b4bb6de3b11e339e4d86c41569eeddcc3c20e.pdf_8_32",
        "observed_type": "text",
        "canon_role": "support_paragraph",
        "text": "-20",
        "bbox": [
          0.4681724842309413,
          0.36046511641975276,
          0.49075975348295336,
          0.3691860460802472
        ],
        "order": 48
      },
      {
        "id": "docling_eastmoney_1746461e6e00efee224a9209974b4bb6de3b11e339e4d86c41569eeddcc3c20e.pdf_8_33",
        "observed_type": "text",
        "canon_role": "support_paragraph",
        "text": "+ 0",
        "bbox": [
          0.4579055446461194,
          0.38070436515181855,
          0.4784394246899517,
          0.3909883717474301
        ],
        "order": 51
      },
      {
        "id": "docling_eastmoney_1746461e6e00efee224a9209974b4bb6de3b11e339e4d86c41569eeddcc3c20e.pdf_8_24",
        "observed_type": "text",
        "canon_role": "support_paragraph",
        "text": "20",
        "bbox": [
          0.09034907632236008,
          0.39680232601277593,
          0.10677618062493627,
          0.40552325567327036
        ],
        "order": 55
      },
      {
        "id": "docling_eastmoney_1746461e6e00efee224a9209974b4bb6de3b11e339e4d86c41569eeddcc3c20e.pdf_8_34",
        "observed_type": "text",
        "canon_role": "support_paragraph",
        "text": "20",
        "bbox": [
          0.4681724850834825,
          0.4026162791566108,
          0.4845995893860588,
          0.40988372069804035
        ],
        "order": 56
      },
      {
        "id": "docling_eastmoney_1746461e6e00efee224a9209974b4bb6de3b11e339e4d86c41569eeddcc3c20e.pdf_8_25",
        "observed_type": "text",
        "canon_role": "support_paragraph",
        "text": "15",
        "bbox": [
          0.09034907608279816,
          0.4127906977885149,
          0.10677618038537433,
          0.4200581393299445
        ],
        "order": 57
      },
      {
        "id": "docling_eastmoney_1746461e6e00efee224a9209974b4bb6de3b11e339e4d86c41569eeddcc3c20e.pdf_8_26",
        "observed_type": "text",
        "canon_role": "support_paragraph",
        "text": "10",
        "bbox": [
          0.09240246440551807,
          0.42877906985428527,
          0.10677618083746618,
          0.4360465113957149
        ],
        "order": 60
      },
      {
        "id": "docling_eastmoney_1746461e6e00efee224a9209974b4bb6de3b11e339e4d86c41569eeddcc3c20e.pdf_8_28",
        "observed_type": "text",
        "canon_role": "support_paragraph",
        "text": "13/04 14/04 15/04 16/04 17/04 18/04 19/04 20/04 21/04 22/04",
        "bbox": [
          0.09848663913395947,
          0.4520089295001801,
          0.4497532299104431,
          0.46253800485026025
        ],
        "order": 65
      },
      {
        "id": "docling_eastmoney_1746461e6e00efee224a9209974b4bb6de3b11e339e4d86c41569eeddcc3c20e.pdf_8_78",
        "observed_type": "text",
        "canon_role": "support_paragraph",
        "text": "16/01 17/01 18/01 19/01 20/01 21/01 22/01",
        "bbox": [
          0.5852156058652175,
          0.4533730156794386,
          0.8788500927658572,
          0.46230158710801
        ],
        "order": 66
      },
      {
        "id": "docling_eastmoney_1746461e6e00efee224a9209974b4bb6de3b11e339e4d86c41569eeddcc3c20e.pdf_8_86",
        "observed_type": "text",
        "canon_role": "support_paragraph",
        "text": "ДТННННН 12",
        "bbox": [
          0.3347022653129465,
          0.7427325579481798,
          0.9383983420792509,
          0.758720930569262
        ],
        "order": 94
      }
    ]
  },
  {
    "eu_id": "EU-0008",
    "kind": "visual_panel",
    "page": "eastmoney_1746461e6e00efee224a9209974b4bb6de3b11e339e4d86c41569eeddcc3c20e.pdf_8",
    "primary_id": "docling_eastmoney_1746461e6e00efee224a9209974b4bb6de3b11e339e4d86c41569eeddcc3c20e.pdf_8_94",
    "source": "visual_seed",
    "member_count": 3,
    "elements": [
      {
        "id": "docling_eastmoney_1746461e6e00efee224a9209974b4bb6de3b11e339e4d86c41569eeddcc3c20e.pdf_8_67",
        "observed_type": "section_header",
        "canon_role": "section_header",
        "text": "#15 #1 СРІ",
        "bbox": [
          0.5215605779612359,
          0.28197674408147955,
          0.7433264893898935,
          0.29513888867430965
        ],
        "order": 31
      },
      {
        "id": "docling_eastmoney_1746461e6e00efee224a9209974b4bb6de3b11e339e4d86c41569eeddcc3c20e.pdf_8_94",
        "observed_type": "picture",
        "canon_role": "picture",
        "text": "",
        "bbox": [
          0.5139532861859507,
          0.29994685061725096,
          0.9446788266607467,
          0.4745695547142208
        ],
        "order": 34
      },
      {
        "id": "docling_eastmoney_1746461e6e00efee224a9209974b4bb6de3b11e339e4d86c41569eeddcc3c20e.pdf_8_77",
        "observed_type": "text",
        "canon_role": "support_paragraph",
        "text": "15/01",
        "bbox": [
          0.5441478450543754,
          0.45348837217986654,
          0.5790554415301559,
          0.46075581372129615
        ],
        "order": 67
      }
    ]
  },
  {
    "eu_id": "EU-0009",
    "kind": "text_cluster_panel",
    "page": "eastmoney_1746461e6e00efee224a9209974b4bb6de3b11e339e4d86c41569eeddcc3c20e.pdf_8",
    "primary_id": "docling_eastmoney_1746461e6e00efee224a9209974b4bb6de3b11e339e4d86c41569eeddcc3c20e.pdf_8_69",
    "source": "text_cluster",
    "member_count": 1,
    "elements": [
      {
        "id": "docling_eastmoney_1746461e6e00efee224a9209974b4bb6de3b11e339e4d86c41569eeddcc3c20e.pdf_8_69",
        "observed_type": "text",
        "canon_role": "support_paragraph",
        "text": "- CPI: 4 A Ft (%)",
        "bbox": [
          0.7823408608546599,
          0.3080357143826136,
          0.8850102650864764,
          0.31696428581118496
        ],
        "order": 37
      }
    ]
  },
  {
    "eu_id": "EU-0010",
    "kind": "text_cluster_panel",
    "page": "eastmoney_1746461e6e00efee224a9209974b4bb6de3b11e339e4d86c41569eeddcc3c20e.pdf_8",
    "primary_id": "docling_eastmoney_1746461e6e00efee224a9209974b4bb6de3b11e339e4d86c41569eeddcc3c20e.pdf_8_29",
    "source": "text_cluster",
    "member_count": 1,
    "elements": [
      {
        "id": "docling_eastmoney_1746461e6e00efee224a9209974b4bb6de3b11e339e4d86c41569eeddcc3c20e.pdf_8_29",
        "observed_type": "text",
        "canon_role": "support_paragraph",
        "text": "(iF)",
        "bbox": [
          0.4414784400721799,
          0.30959302315968046,
          0.4804928122892164,
          0.3168604651741628
        ],
        "order": 38
      }
    ]
  },
  {
    "eu_id": "EU-0011",
    "kind": "visual_panel",
    "page": "eastmoney_1746461e6e00efee224a9209974b4bb6de3b11e339e4d86c41569eeddcc3c20e.pdf_8",
    "primary_id": "docling_eastmoney_1746461e6e00efee224a9209974b4bb6de3b11e339e4d86c41569eeddcc3c20e.pdf_8_92",
    "source": "visual_seed",
    "member_count": 1,
    "elements": [
      {
        "id": "docling_eastmoney_1746461e6e00efee224a9209974b4bb6de3b11e339e4d86c41569eeddcc3c20e.pdf_8_92",
        "observed_type": "picture",
        "canon_role": "picture",
        "text": "",
        "bbox": [
          0.07331095814272455,
          0.5136550179196505,
          0.501020253929867,
          0.6829145610103142
        ],
        "order": 72
      }
    ]
  }
]