[
  {
    "eu_id": "EU-0001",
    "kind": "table_panel",
    "page": "scihub_s00784-003-0233-4.pdf_1",
    "primary_id": "docling_scihub_s00784-003-0233-4.pdf_1_9",
    "source": "visual_seed",
    "member_count": 8,
    "elements": [
      {
        "id": "docling_scihub_s00784-003-0233-4.pdf_1_1",
        "observed_type": "caption",
        "canon_role": "support_paragraph",
        "text": "Table 1 Clinical data (Rec recurrence, Met metastasis, Pr primary, Tmf temporomandibular fossa, Smr submandibular region, S surgery, R radiation therapy, C chemotherapy, UR primary site of",
        "bbox": [
          0.08045978280417823,
          0.06540697677385623,
          0.49233716425343194,
          0.1002906975212019
        ],
        "order": 2
      },
      {
        "id": "docling_scihub_s00784-003-0233-4.pdf_1_2",
        "observed_type": "text",
        "canon_role": "support_paragraph",
        "text": "tumor unresectable, L regional lymph node metastasis, D distant metastasis, Ao alive without disease, Ac alive with disease, Dc died of disease)",
        "bbox": [
          0.5075991148285159,
          0.06540697688286778,
          0.9195402264550807,
          0.09909090415899273
        ],
        "order": 3
      },
      {
        "id": "docling_scihub_s00784-003-0233-4.pdf_1_9",
        "observed_type": "table",
        "canon_role": "table",
        "text": "Case no. | Diagnosis | Case Sex | Age (years) | Site | Treatment | Rec Met Follow-up | Status | Osteosarcoma | Pr | M | Tmf | S+R+C | 7 years 1 month | Ao | Osteosarcoma | Pr | Maxilla | 9 years 6 months | Ao | Osteosarcoma | Pr | Mandible | + | 111 | 6 years 4 months | Ao | Osteosarcoma | Pr | Mandible | D | 5 years | Dc | Osteosarcoma | Pr | Mandible | D | 13 years 7 months | Ac | Osteosarcoma | Pr | M | Maxilla | S+C | 3 years 2 months | Ao | Osteosarcoma | Rec | M | Maxillary sinus | S+R+C | 4 years 1 month | Dc | Osteosarcoma | Rec | F | Maxilla | S+R+C | D | 3 years 3 months | Dc | 9 | Osteosarcoma | Rec | M | Mandible | S | 9 years 3 months | Ao | 10 | MFH | Pr | M | Maxillary sinus | S+C | + | 1 year 4 months | Dc | 11 | MFH | Pr | Mandible | S | + | 2 years | 12 | MFH | Pr | Smr | S+R | 8 years 1 month | Ao | 13 | MFH | Rec | M | Mandible | S | 4 years 6 months | Ao | 14 | MFH | Pr | Maxilla | 11 years 8 months | Ao | 15 | MFH | Pr | Maxillary sinus | S | 9 months | Dc | 16 | MFH | Pr | Maxillary sinus | 5 years | Ao | 17 | Rhabdomyosarcoma | Pr | M | Buccal mucosa | S | 17 years 3 months | Ao | 18 | Rhabdomyosarcoma | Pr | F | Buccal mucosa | 1 year 6 months | Dc | 19 | Rhabdomyosarcoma | Pr | M | Maxilla | +111 | D | 2 years 3 months | De | 20 | Rhabdomyosarcoma | Pr | M | Maxilla | UR | L+D | 4 months | Dc | 21 | Rhabdomyosarcoma | Pr | Mandible | S | 2 years 9 months | Ao | Fibrosarcoma | Pr | F | Mandible | 9 years 9 months | Ao | Fibrosarcoma | Pr | F | Mandible | 111 | 11 years 6 months | Ao | Fibrosarcoma | Pr | F | Mandible | 1010 | 19 years | Ao | Plasmacytoma | Pr | M | Mandible | - | 14 years | Ao | Plasmacytoma | Pr | M | Maxillary sinus | 5 years 1 month | Ao | Leiomyosarcoma | Rec | M | Maxilla | UR | L+D | 2 months | Dc | Leiomyosarcoma | Pr | M | Mandible | S | - | D | 8 years | Ac | 29 | Angiosarcoma | Pr | M | Tmf | UR | 4 years | Dc | 30 | Angiosarcoma | Pr | M | Maxilla | + + + | L | 8 months | Dc | 31 | Liposarcoma | Pr | F | Buccal mucosa | 2 years 10 months | Dc | 32 | Ameloblastic fibro- sarcoma | Rec | M | Mandible | S | 5 months | Dc",
        "bbox": [
          0.07899365249144548,
          0.10387542738601846,
          0.9200680196754008,
          0.531235447830697
        ],
        "order": 4
      },
      {
        "id": "docling_scihub_s00784-003-0233-4.pdf_1_3",
        "observed_type": "text",
        "canon_role": "support_paragraph",
        "text": "The most common histological type was osteosarcoma (n=9; 28%), followed by malignant fibrous histiocytoma (MFH;(n=7, 22%), rhabdomyosarcoma (n=5, 16%), fibrosarcoma (n=3, 9%), plasmacytoma (n=2, 6%), leiomyosarcoma (n=2, 6%, angiosarcoma (n=2. 6%), and liposarcoma (n=1, 3%), ameloblastic fibrosarcoma (n=1, 3%). The histological subtypes of osteosarcoma were chondroblastic (n=5; Table 1, nos. 1, 2, 6, 8, 9), osteoblastic (n=3, nos. 3, 4, 7), and telangiectatic (n=1, no. 5). In rhabdomyosarcoma, the histological subtypes were alveolar (n=3, nos. 17, 18, 20) and pleomorphic (n=2, nos. 19, 21). Patients with malignant lymphoma were excluded from this study because malignant lymphoma is a systemic disease. Two cases of plasmacytoma were both of the solitary type, therefore these cases were included.",
        "bbox": [
          0.08043406169117447,
          0.5624999998129792,
          0.49239172406607995,
          0.713662790631667
        ],
        "order": 5
      },
      {
        "id": "docling_scihub_s00784-003-0233-4.pdf_1_6",
        "observed_type": "text",
        "canon_role": "support_paragraph",
        "text": "Fourteen patients of 32 were making satisfactory progress without local recurrence or metastasis at a mean follow-up period of 8.5 years, ranging from 2 years 3 months to 19 years. Local recurrence was found in 10 cases (31%) and metastasis in 11 (34%). Among 10 patients with local recurrence, 3 are alive after 6-17 years, and 7 died of their tumors after 5 months to 4 years. Among the 3 patients alive, one (no. 3) was treated by surgery and the other (no. 17) by surgery and postoperative radiation therapy (50 Gy) after local recurrence was found. These two patients are alive without evidence of disease over 3 years and 7 years after salvage treatment. Another patient (no. 5) was treated by preoperative radiation therapy (45 Gy) and surgery for local recurrence. The local recurrence was controlled, but this patient developed distant metastasis to the lung.",
        "bbox": [
          0.5055756471073498,
          0.6527707600066481,
          0.9214559311312153,
          0.8706395345646853
        ],
        "order": 7
      },
      {
        "id": "docling_scihub_s00784-003-0233-4.pdf_1_8",
        "observed_type": "text",
        "canon_role": "support_paragraph",
        "text": "Surgical resection (S) alone was carried out in 15 patients. Triple modality of S, radiation therapy (R) and chemotherapy (C) was performed in 6, combined therapy of S/C in 4, and S/R was in 4. We judged that the primary tumors were unresectable in three cases; therefore combined therapy of R and C was given to these 3 patients. Radiation therapy was given preoperatively in 6 cases, postoperatively in 3 and both in 1. The doses used varied from 18 to 80 Gy, with an average of 48 Gy. All radiation therapy was external irradiation. The fraction sizes were 2.5 Gy, treating 4 days in a week. Chemotherapy was given preoperatively in 8 cases and postoperatively in 2. The chemotherapy regimens were varied.",
        "bbox": [
          0.08045976833918896,
          0.712209302536606,
          0.49233716304511893,
          0.8415697672900657
        ],
        "order": 8
      },
      {
        "id": "docling_scihub_s00784-003-0233-4.pdf_1_4",
        "observed_type": "text",
        "canon_role": "support_paragraph",
        "text": "Treatment was determined according to the experience of the surgeon. This resulted in a lack of unity in the treatment protocol. The common agents were cisplatin (n=5), 5-fluorouracil (n=4), and doxorubicin (n=4). The regional intra-arterial infusion chemotherapy administered via the superficial temporal artery was given in 9 of 11 patients who had sarcoma of the maxilla, maxillary sinus, or the temporomandibular fossa. The survival rate and survival curve were calculated by the Kaplan-Meier method using SPSS for Windows, version 10.",
        "bbox": [
          0.08045976679065774,
          0.8415178571738596,
          0.49233716815144907,
          0.914244185835487
        ],
        "order": 9
      },
      {
        "id": "docling_scihub_s00784-003-0233-4.pdf_1_7",
        "observed_type": "text",
        "canon_role": "support_paragraph",
        "text": "The 5-year survival rate of patient with local recurrence was 30% (Fig. 1). Among 11 patients with metastases 9 died",
        "bbox": [
          0.5057471357270223,
          0.8720238093559579,
          0.919540236965306,
          0.9011627910525469
        ],
        "order": 10
      }
    ]
  },
  {
    "eu_id": "EU-0002",
    "kind": "section_text_panel",
    "page": "scihub_s00784-003-0233-4.pdf_1",
    "primary_id": "docling_scihub_s00784-003-0233-4.pdf_1_5",
    "source": "header_anchor",
    "member_count": 1,
    "elements": [
      {
        "id": "docling_scihub_s00784-003-0233-4.pdf_1_5",
        "observed_type": "section_header",
        "canon_role": "section_header",
        "text": "Results",
        "bbox": [
          0.5076428214770562,
          0.6278546962694886,
          0.5670698231905144,
          0.6410406524448538
        ],
        "order": 6
      }
    ]
  }
]