[
  {
    "eu_id": "EU-0001",
    "kind": "text_cluster_panel",
    "page": "yanbaor2_yanbaoPPT_3302",
    "primary_id": "docling_yanbaor2_yanbaoPPT_3302_0",
    "source": "text_cluster",
    "member_count": 1,
    "elements": [
      {
        "id": "docling_yanbaor2_yanbaoPPT_3302_0",
        "observed_type": "text",
        "canon_role": "support_paragraph",
        "text": "495, 211",
        "bbox": [
          0.3939340800383651,
          0.16269841312265101,
          0.5256673470747925,
          0.180307540106778
        ],
        "order": 1
      }
    ]
  },
  {
    "eu_id": "EU-0002",
    "kind": "text_cluster_panel",
    "page": "yanbaor2_yanbaoPPT_3302",
    "primary_id": "docling_yanbaor2_yanbaoPPT_3302_1",
    "source": "text_cluster",
    "member_count": 4,
    "elements": [
      {
        "id": "docling_yanbaor2_yanbaoPPT_3302_1",
        "observed_type": "text",
        "canon_role": "support_paragraph",
        "text": "15 MAN THrT.",
        "bbox": [
          0.20739219901566133,
          0.44320436467443153,
          0.5318275114464917,
          0.6220930227200874
        ],
        "order": 2
      },
      {
        "id": "docling_yanbaor2_yanbaoPPT_3302_2",
        "observed_type": "text",
        "canon_role": "support_paragraph",
        "text": "SUSA Robin Huettemann НИДЕРТ James Polyblank FLeda Zaharieva € * 7 43 7 Sr Shannon Varney € te",
        "bbox": [
          0.2073922067978288,
          0.6918604651096122,
          0.8932237925787392,
          0.7267441860774034
        ],
        "order": 3
      },
      {
        "id": "docling_yanbaor2_yanbaoPPT_3302_3",
        "observed_type": "text",
        "canon_role": "support_paragraph",
        "text": "1F * R it Mahima Agarwal, Selma Belghiti, Chien-Teng Chia, Jonas Chinczewski, Emmanuel Clarke, Deniz Cultu, Philipp Horsch, Varun John Jacob, Sylvain Johansson, Philipp Klais, Bernhard Kotanko, Christie McNeill, Jörg Mußhoff#»Fritz",
        "bbox": [
          0.20739219005998702,
          0.7529069768586429,
          0.8870636394403559,
          0.7761627904489803
        ],
        "order": 4
      },
      {
        "id": "docling_yanbaor2_yanbaoPPT_3302_4",
        "observed_type": "text",
        "canon_role": "support_paragraph",
        "text": "#*FT # 02023 # H 432 7. 176 Рт#*.",
        "bbox": [
          0.2073921990289341,
          0.819692460413138,
          0.39835729239817064,
          0.8284883717706543
        ],
        "order": 5
      }
    ]
  },
  {
    "eu_id": "EU-0003",
    "kind": "text_cluster_panel",
    "page": "yanbaor2_yanbaoPPT_3302",
    "primary_id": "docling_yanbaor2_yanbaoPPT_3302_5",
    "source": "text_cluster",
    "member_count": 1,
    "elements": [
      {
        "id": "docling_yanbaor2_yanbaoPPT_3302_5",
        "observed_type": "footnote",
        "canon_role": "support_paragraph",
        "text": "35 7#557» (Pensions at a glance 2021- Ages and years) , OECD, 1Ht i: 2023 4175 El o",
        "bbox": [
          0.20533880980696814,
          0.9055232559007969,
          0.8726899380034874,
          0.9288194446182417
        ],
        "order": 6
      }
    ]
  }
]