[
  {
    "chunk_id": "docling_notes_f7f010b78016aeebd76e56d9283eb67f_28_1",
    "text": "Date",
    "canon_role": "support_paragraph",
    "bbox": [
      0.763860371403747,
      0.09011627917311256,
      0.8234086244210308,
      0.10029069742572456
    ],
    "page": "notes_f7f010b78016aeebd76e56d9283eb67f_28",
    "order": 2
  },
  {
    "chunk_id": "docling_notes_f7f010b78016aeebd76e56d9283eb67f_28_2",
    "text": "80: close, closely",
    "canon_role": "support_paragraph",
    "bbox": [
      0.10417257131931806,
      0.12391500485198129,
      0.3229369212106438,
      0.1521077709810057
    ],
    "page": "notes_f7f010b78016aeebd76e56d9283eb67f_28",
    "order": 3
  },
  {
    "chunk_id": "docling_notes_f7f010b78016aeebd76e56d9283eb67f_28_3",
    "text": "closely connected, stand close",
    "canon_role": "support_paragraph",
    "bbox": [
      0.15195071746902958,
      0.1860119049645927,
      0.5277207356315865,
      0.21511627872239397
    ],
    "page": "notes_f7f010b78016aeebd76e56d9283eb67f_28",
    "order": 4
  },
  {
    "chunk_id": "docling_notes_f7f010b78016aeebd76e56d9283eb67f_28_4",
    "text": "ill, sick",
    "canon_role": "support_paragraph",
    "bbox": [
      0.10472279191485696,
      0.2180059526530498,
      0.26694045406050226,
      0.23983134947844653
    ],
    "page": "notes_f7f010b78016aeebd76e56d9283eb67f_28",
    "order": 5
  },
  {
    "chunk_id": "docling_notes_f7f010b78016aeebd76e56d9283eb67f_28_5",
    "text": "88. good, well",
    "canon_role": "support_paragraph",
    "bbox": [
      0.10053234326961022,
      0.2787991775233297,
      0.27729106466734693,
      0.30695663688832703
    ],
    "page": "notes_f7f010b78016aeebd76e56d9283eb67f_28",
    "order": 6
  },
  {
    "chunk_id": "docling_notes_f7f010b78016aeebd76e56d9283eb67f_28_6",
    "text": "89 quiet, silent, still",
    "canon_role": "support_paragraph",
    "bbox": [
      0.10266940458589296,
      0.3386627910077101,
      0.37595611965160225,
      0.3714311407312361
    ],
    "page": "notes_f7f010b78016aeebd76e56d9283eb67f_28",
    "order": 7
  },
  {
    "chunk_id": "docling_notes_f7f010b78016aeebd76e56d9283eb67f_28_7",
    "text": "9o. hard, hardly",
    "canon_role": "support_paragraph",
    "bbox": [
      0.10241514519605605,
      0.4322581380827532,
      0.30826247569710713,
      0.4645441879104502
    ],
    "page": "notes_f7f010b78016aeebd76e56d9283eb67f_28",
    "order": 8
  },
  {
    "chunk_id": "docling_notes_f7f010b78016aeebd76e56d9283eb67f_28_8",
    "text": "hard ts, hardly nr. work hard, I can hardly believe it.",
    "canon_role": "support_paragraph",
    "bbox": [
      0.1436022458111426,
      0.4634600692029838,
      0.8502045388510646,
      0.4960562410513415
    ],
    "page": "notes_f7f010b78016aeebd76e56d9283eb67f_28",
    "order": 9
  },
  {
    "chunk_id": "docling_notes_f7f010b78016aeebd76e56d9283eb67f_28_9",
    "text": "91. able, capable",
    "canon_role": "support_paragraph",
    "bbox": [
      0.10242661827224728,
      0.4962525266856575,
      0.3082510017786747,
      0.5284567762341911
    ],
    "page": "notes_f7f010b78016aeebd76e56d9283eb67f_28",
    "order": 10
  },
  {
    "chunk_id": "docling_notes_f7f010b78016aeebd76e56d9283eb67f_28_10",
    "text": "able 57/ed to do SPI, capable 5 of FE: He is capable of doing ...",
    "canon_role": "support_paragraph",
    "bbox": [
      0.14083458851174618,
      0.520001332949168,
      0.9061713075354847,
      0.562914959059911
    ],
    "page": "notes_f7f010b78016aeebd76e56d9283eb67f_28",
    "order": 11
  },
  {
    "chunk_id": "docling_notes_f7f010b78016aeebd76e56d9283eb67f_28_11",
    "text": "almost, nearly",
    "canon_role": "support_paragraph",
    "bbox": [
      0.09856262910471368,
      0.552325582658472,
      0.33539242804654884,
      0.5898184331286365
    ],
    "page": "notes_f7f010b78016aeebd76e56d9283eb67f_28",
    "order": 12
  },
  {
    "chunk_id": "docling_notes_f7f010b78016aeebd76e56d9283eb67f_28_12",
    "text": "93. Late, Lately",
    "canon_role": "support_paragraph",
    "bbox": [
      0.10456748054602553,
      0.6201023517211085,
      0.30200335813148665,
      0.6502464849861648
    ],
    "page": "notes_f7f010b78016aeebd76e56d9283eb67f_28",
    "order": 13
  },
  {
    "chunk_id": "docling_notes_f7f010b78016aeebd76e56d9283eb67f_28_13",
    "text": "I haven't seen him lately.",
    "canon_role": "support_paragraph",
    "bbox": [
      0.533357981930156,
      0.6472752709022556,
      0.8569811365897347,
      0.6822209291773148
    ],
    "page": "notes_f7f010b78016aeebd76e56d9283eb67f_28",
    "order": 14
  },
  {
    "chunk_id": "docling_notes_f7f010b78016aeebd76e56d9283eb67f_28_14",
    "text": "94. living, alive, live, lively",
    "canon_role": "support_paragraph",
    "bbox": [
      0.1026694034425859,
      0.6829060345402101,
      0.4645159139871488,
      0.714901001773777
    ],
    "page": "notes_f7f010b78016aeebd76e56d9283eb67f_28",
    "order": 15
  },
  {
    "chunk_id": "docling_notes_f7f010b78016aeebd76e56d9283eb67f_28_15",
    "text": "all the living people = all the people alive.",
    "canon_role": "support_paragraph",
    "bbox": [
      0.16632443413667622,
      0.7775297628001953,
      0.7043121251377931,
      0.8095930237111985
    ],
    "page": "notes_f7f010b78016aeebd76e56d9283eb67f_28",
    "order": 16
  },
  {
    "chunk_id": "docling_notes_f7f010b78016aeebd76e56d9283eb67f_28_16",
    "text": "excited, exciting",
    "canon_role": "support_paragraph",
    "bbox": [
      0.10332449390200937,
      0.8011039726806763,
      0.35552385533826114,
      0.8408345404614284
    ],
    "page": "notes_f7f010b78016aeebd76e56d9283eb67f_28",
    "order": 17
  },
  {
    "chunk_id": "docling_notes_f7f010b78016aeebd76e56d9283eb67f_28_17",
    "text": "I'm excited. The news is exciting.",
    "canon_role": "support_paragraph",
    "bbox": [
      0.16211441903730525,
      0.8666177711591773,
      0.6106945940546039,
      0.900578034093544
    ],
    "page": "notes_f7f010b78016aeebd76e56d9283eb67f_28",
    "order": 18
  },
  {
    "chunk_id": "docling_notes_f7f010b78016aeebd76e56d9283eb67f_28_18",
    "text": "96: deep, deeply",
    "canon_role": "support_paragraph",
    "bbox": [
      0.10677618187979547,
      0.9010416659625882,
      0.3162217617308173,
      0.9331395354117799
    ],
    "page": "notes_f7f010b78016aeebd76e56d9283eb67f_28",
    "order": 19
  }
]