[
  {
    "chunk_id": "mineru_notes_f7f010b78016aeebd76e56d9283eb67f_68_0",
    "text": "10.引导结果状语从句的从属益词有：s0 that(结果是)和so/such…that. (如此…以至于)等.",
    "canon_role": "support_paragraph",
    "bbox": [
      0.09762900976290098,
      0.11451135241855874,
      0.9372384937238494,
      0.17242513984863442
    ],
    "page": "notes_f7f010b78016aeebd76e56d9283eb67f_68",
    "order": 1
  },
  {
    "chunk_id": "mineru_notes_f7f010b78016aeebd76e56d9283eb67f_68_1",
    "text": "It was very cold, so that tho wator in the bowl froze It is such a heavy box that nobody can move it.",
    "canon_role": "support_paragraph",
    "bbox": [
      0.13668061366806136,
      0.17900625205659756,
      0.7661552766155276,
      0.23757815070746957
    ],
    "page": "notes_f7f010b78016aeebd76e56d9283eb67f_68",
    "order": 2
  },
  {
    "chunk_id": "mineru_notes_f7f010b78016aeebd76e56d9283eb67f_68_2",
    "text": "11.引导比较状语从同的从属连词有：as…as1与…一样).ntas/so…as… (不及，赶不上)，和hat(比)等.",
    "canon_role": "support_paragraph",
    "bbox": [
      0.10134821013482101,
      0.24086870681145114,
      0.9418874941887494,
      0.2987824942415268
    ],
    "page": "notes_f7f010b78016aeebd76e56d9283eb67f_68",
    "order": 3
  },
  {
    "chunk_id": "mineru_notes_f7f010b78016aeebd76e56d9283eb67f_68_3",
    "text": "I know yomu better than she does. He works as carefully as she. I canit run as/so fast as you.",
    "canon_role": "support_paragraph",
    "bbox": [
      0.13296141329614133,
      0.30536360644948995,
      0.5588098558809856,
      0.3942086212569924
    ],
    "page": "notes_f7f010b78016aeebd76e56d9283eb67f_68",
    "order": 4
  },
  {
    "chunk_id": "mineru_notes_f7f010b78016aeebd76e56d9283eb67f_68_4",
    "text": "2.引导名词性从句的从属连词有：that和i计/whether(是否)等. We know that the earth goes around the sun. (宾语从句) Whether he' go there hosn't been decided.(主语从向) [注意]在时间状语从句和条件状语从句中，如果主句是将来时，从句要 用一般现在时.",
    "canon_role": "support_paragraph",
    "bbox": [
      0.10599721059972106,
      0.3928923988153998,
      0.9325894932589494,
      0.5462323132609411
    ],
    "page": "notes_f7f010b78016aeebd76e56d9283eb67f_68",
    "order": 5
  },
  {
    "chunk_id": "mineru_notes_f7f010b78016aeebd76e56d9283eb67f_68_5",
    "text": "",
    "canon_role": "picture",
    "bbox": [
      0.07810320781032078,
      0.6627179993418888,
      0.6164574616457462,
      0.7015465613688714
    ],
    "page": "notes_f7f010b78016aeebd76e56d9283eb67f_68",
    "order": 6
  }
]